simple_summarizer/__init__.py
simple_summarizer/summarize.py
simple_summarizer-0.1.0.dist-info/licenses/LICENSE
simple_summarizer-0.1.0.dist-info/METADATA
simple_summarizer-0.1.0.dist-info/WHEEL
simple_summarizer-0.1.0.dist-info/entry_points.txt
simple_summarizer-0.1.0.dist-info/top_level.txt
simple_summarizer-0.1.0.dist-info/RECORD
