Metadata-Version: 2.4
Name: simple_summarizer
Version: 0.1.0
Summary: A simple text summarization library using NLTK
Home-page: https://github.com/arhaan15/simple_summarizer
Author: Arhaan Motiwala
Author-email: arhaanmotiwala11@gmail.com
Classifier: Programming Language :: Python :: 3
Classifier: License :: OSI Approved :: MIT License
Classifier: Operating System :: OS Independent
Requires-Python: >=3.6
License-File: LICENSE
Requires-Dist: nltk
Dynamic: author
Dynamic: author-email
Dynamic: classifier
Dynamic: description
Dynamic: description-content-type
Dynamic: home-page
Dynamic: license-file
Dynamic: requires-dist
Dynamic: requires-python
Dynamic: summary
